{"skeleton":{"width":195.76,"height":189.62,"fps":24,"spine":"3.6.0","hash":" ","name":"Armature"},"bones":[{"name":"root"},{"x":-78.35,"y":77.85,"name":"Sl_02","parent":"root"},{"x":74.4,"y":81.8,"name":"zjh_fire","parent":"root"},{"length":64,"x":32.05,"y":-0.45,"rotation":69.8276,"name":"zjh_boom","parent":"root"},{"x":-2,"y":-26.2,"name":"zjh_font","parent":"root"},{"x":15.95,"y":-65.65,"name":"zjh_chip","parent":"root"},{"x":79.5,"y":-70.65,"name":"zjh_fchip","parent":"root"},{"x":10.05,"y":-39.6,"name":"Comp 1_003","parent":"root"},{"length":14,"x":52.25,"y":1.95,"rotation":53.1301,"name":"zjh_chip00","parent":"root"},{"length":10,"x":78.3,"y":5.9,"rotation":39.234,"name":"zjh_chip01","parent":"root"},{"length":10,"x":-17.35,"y":9.35,"rotation":42.527,"name":"zjh_chip02","parent":"root"},{"length":74,"x":-43.25,"y":13.4,"rotation":67.3088,"name":"zjh_c3","parent":"root"},{"length":71,"x":-51.1,"y":8.45,"rotation":77.4495,"name":"zjh_c2","parent":"root"},{"length":82,"x":-46.7,"y":-4.65,"rotation":94.3213,"name":"zjh_c1","parent":"root"},{"length":26,"x":-63.75,"y":9.5,"rotation":157.1663,"name":"zjh_bckchip","parent":"root"}],"slots":[{"name":"zjh_bckchip","bone":"zjh_bckchip","attachment":"zjh_bckchip"},{"name":"zjh_c1","bone":"zjh_c1","attachment":"zjh_c1"},{"name":"zjh_c2","bone":"zjh_c2","attachment":"zjh_c2"},{"name":"zjh_c3","bone":"zjh_c3","attachment":"zjh_c3"},{"name":"zjh_boom","bone":"zjh_boom","attachment":"zjh_boom"},{"name":"zjh_chip02","bone":"zjh_chip02","attachment":"zjh_chip02"},{"name":"zjh_fire","bone":"zjh_fire","attachment":"zjh_fire"},{"name":"zjh_chip00","bone":"zjh_chip00","attachment":"zjh_chip00"},{"name":"zjh_chip01","bone":"zjh_chip01","attachment":"zjh_chip01"},{"name":"zjh_font","bone":"zjh_font","attachment":"zjh_font"},{"name":"Comp 1_003","bone":"Comp 1_003","attachment":"mask/Comp 1_009"},{"name":"zjh_fchip","bone":"zjh_fchip","attachment":"zjh_fchip"},{"name":"zjh_chip","bone":"zjh_chip","attachment":"zjh_chip"},{"name":"Sl_02","bone":"Sl_02","attachment":"Sl_02"}],"skins":{"default":{"zjh_c2":{"zjh_c2":{"name":"zjh_c2","width":87,"height":89,"x":36.14,"y":-2.11,"rotation":-77.45}},"zjh_font":{"zjh_font":{"name":"zjh_font","width":177,"height":107,"x":-0.74,"y":-10.71}},"zjh_chip00":{"zjh_chip00":{"name":"zjh_chip00","width":37,"height":40,"x":0.65,"y":-5.39,"rotation":-53.13}},"zjh_fchip":{"zjh_fchip":{"name":"zjh_fchip","width":38,"height":28,"x":-1.41,"y":-4.15}},"zjh_chip02":{"zjh_chip02":{"name":"zjh_chip02","width":29,"height":28,"x":-0.44,"y":-2.98,"rotation":-42.53}},"zjh_c1":{"zjh_c1":{"name":"zjh_c1","width":97,"height":98,"x":39.96,"y":0.45,"rotation":-94.32}},"zjh_bckchip":{"zjh_bckchip":{"name":"zjh_bckchip","width":39,"height":40,"x":11.96,"y":2.63,"rotation":-157.17}},"zjh_c3":{"zjh_c3":{"name":"zjh_c3","width":75,"height":85,"x":36.37,"y":-3.89,"rotation":-67.31}},"Comp 1_003":{"mask/Comp 1_003":{"name":"mask/Comp 1_003","width":41,"height":85,"x":-12.01,"y":2.92},"mask/Comp 1_004":{"name":"mask/Comp 1_004","width":66,"height":98,"x":-12.01,"y":2.92},"mask/Comp 1_005":{"name":"mask/Comp 1_005","width":69,"height":107,"x":-12.01,"y":2.92},"mask/Comp 1_006":{"name":"mask/Comp 1_006","width":67,"height":100,"x":-12.01,"y":2.92},"mask/Comp 1_007":{"name":"mask/Comp 1_007","width":56,"height":79,"x":-12.01,"y":2.92},"mask/Comp 1_008":{"name":"mask/Comp 1_008","width":55,"height":70,"x":-12.01,"y":2.92},"mask/Comp 1_009":{"name":"mask/Comp 1_009","width":39,"height":66,"x":-12.01,"y":2.92}},"zjh_chip01":{"zjh_chip01":{"name":"zjh_chip01","width":28,"height":29,"x":-0.19,"y":-4.07,"rotation":-39.23}},"zjh_fire":{"zjh_fire":{"name":"zjh_fire","width":31,"height":26,"x":0.41,"y":-0.42}},"zjh_chip":{"zjh_chip":{"name":"zjh_chip","width":53,"height":38,"x":1.25,"y":-1.6}},"zjh_boom":{"zjh_boom":{"name":"zjh_boom","width":91,"height":104,"x":31.11,"y":7.77,"rotation":-69.83}},"Sl_02":{"Sl_02":{"name":"Sl_02","width":41,"height":43,"x":0.64,"y":-0.13}}}},"animations":{"zjh":{"bones":{"Sl_02":{"rotate":[{"time":0,"curve":"stepped","angle":0},{"time":1.2083,"angle":0},{"time":2,"angle":-140.5}],"scale":[{"time":0,"curve":"stepped","x":1,"y":1},{"time":1.2083,"x":0.01,"y":0.01},{"time":1.4583,"x":1,"y":1},{"time":2,"x":0.01,"y":0.01}],"shear":[{"time":0,"curve":"stepped"},{"time":1.2083},{"time":2}]},"zjh_fire":{"translate":[{"time":0},{"time":0.6667,"y":5.97},{"time":2}],"scale":[{"time":0,"x":1,"y":1},{"time":0.0833,"x":1.2,"y":1.2},{"time":0.1666,"x":1,"y":1},{"time":0.2499,"x":1.2,"y":1.2},{"time":0.3332,"x":1,"y":1},{"time":0.4165,"x":1.2,"y":1.2},{"time":0.4998,"x":1,"y":1},{"time":0.5831,"x":1.2,"y":1.2},{"time":0.6664,"x":1,"y":1},{"time":0.7497,"x":1.2,"y":1.2},{"time":0.833,"x":1,"y":1},{"time":0.9163,"x":1.2,"y":1.2},{"time":0.9996,"x":1,"y":1},{"time":1.0829,"x":1.2,"y":1.2},{"time":1.1662,"x":1,"y":1},{"time":1.2495,"x":1.2,"y":1.2},{"time":1.3328,"x":1,"y":1},{"time":1.4161,"x":1.2,"y":1.2},{"time":1.4994,"x":1,"y":1},{"time":1.5827,"x":1.2,"y":1.2},{"time":1.666,"x":1,"y":1},{"time":1.7493,"x":1.2,"y":1.2},{"time":1.8326,"x":1,"y":1},{"time":1.9159,"x":1.2,"y":1.2},{"time":1.9992,"x":1,"y":1}]},"zjh_boom":{"translate":[{"time":0},{"time":0.6667,"y":7.88},{"time":2}]},"zjh_chip":{"translate":[{"time":0},{"time":1.25,"y":1.96},{"time":2}]},"zjh_fchip":{"translate":[{"time":0},{"time":0.9167,"x":4.91,"y":-3.92},{"time":2}]},"zjh_chip00":{"translate":[{"time":0},{"time":0.7917,"x":2.89,"y":4.1},{"time":2}],"rotate":[{"time":0,"angle":0},{"time":0.7917,"angle":-5.5},{"time":2,"angle":0}],"shear":[{"time":0},{"time":0.7917},{"time":2}]},"zjh_chip01":{"translate":[{"time":0},{"time":1.2083,"x":2.43,"y":2.89},{"time":2}]},"zjh_chip02":{"translate":[{"time":0},{"time":0.6667,"x":-2},{"time":2}],"rotate":[{"time":0,"angle":0},{"time":0.6667,"angle":39},{"time":2,"angle":0}],"shear":[{"time":0},{"time":0.6667},{"time":2}]},"zjh_c3":{"translate":[{"time":0,"y":-2.65},{"time":0.4583},{"time":0.9583,"y":3.74},{"time":1.625},{"time":2,"y":-2.65}],"rotate":[{"time":0,"curve":[0,0,0.3747203579418345,0.9943396226415094],"angle":8},{"time":0.4583,"angle":0},{"time":1.625,"curve":[0,0,0.36017897091722584,0.9716981132075472],"angle":0},{"time":2,"angle":8}],"shear":[{"time":0,"curve":[0,0,0.3747203579418345,0.9943396226415094]},{"time":0.4583},{"time":1.625,"curve":[0,0,0.36017897091722584,0.9716981132075472]},{"time":2}]},"zjh_c2":{"translate":[{"time":0},{"time":0.4583},{"time":0.9583,"y":3.68},{"time":1.625}],"rotate":[{"time":0,"curve":[0,0,0.35794183445190164,1.0028301886792454],"angle":-2},{"time":0.4583,"angle":0},{"time":1.625,"curve":[0,0,0.3389261744966443,0.9349056603773584],"angle":0},{"time":2,"angle":-2}],"shear":[{"time":0,"curve":[0,0,0.35794183445190164,1.0028301886792454]},{"time":0.4583},{"time":1.625,"curve":[0,0,0.3389261744966443,0.9349056603773584]},{"time":2}]},"zjh_c1":{"translate":[{"time":0},{"time":0.4583},{"time":0.9583,"y":6.29},{"time":1.625}],"rotate":[{"time":0,"curve":[0,0,0.3501118568232662,1.005660377358491],"angle":-10},{"time":0.4583,"angle":0},{"time":1.625,"curve":[0,0,0.33445190156599547,0.9773584905660376],"angle":0},{"time":2,"angle":-10}],"shear":[{"time":0,"curve":[0,0,0.3501118568232662,1.005660377358491]},{"time":0.4583},{"time":1.625,"curve":[0,0,0.33445190156599547,0.9773584905660376]},{"time":2}]},"zjh_bckchip":{"translate":[{"time":0,"x":1.69},{"time":0.375},{"time":1.0833,"y":2.65},{"time":1.625},{"time":2,"x":1.69}],"rotate":[{"time":0,"angle":-6.5},{"time":0.375,"angle":0},{"time":1.625,"angle":0},{"time":2,"angle":-6.5}],"shear":[{"time":0},{"time":0.375},{"time":1.625},{"time":2}]}},"slots":{"Comp 1_003":{"attachment":[{"time":0,"name":"mask/Comp 1_009"},{"time":0.7917,"name":"mask/Comp 1_003"},{"time":0.875,"name":"mask/Comp 1_004"},{"time":0.9583,"name":"mask/Comp 1_005"},{"time":1.0416,"name":"mask/Comp 1_006"},{"time":1.1249,"name":"mask/Comp 1_007"},{"time":1.2082,"name":"mask/Comp 1_008"},{"time":1.2915,"name":"mask/Comp 1_009"}],"color":[{"time":0,"color":"FFFFFF00"},{"time":0.8333,"color":"FFFFFF00"},{"time":1.0416,"color":"FFFFFFFF"},{"time":1.1249,"color":"FFFFFFFF"},{"time":1.4166,"color":"FFFFFF00"}]},"Sl_02":{"color":[{"time":0,"color":"FFFFFF00"},{"time":1.2083,"color":"FFFFFF00"},{"time":1.4583,"color":"FFFFFFFF"},{"time":2,"color":"FFFFFF00"}]}}}}}